<?xml version="1.0" ?><annotation>
	<folder>wangzhihe</folder>
	<filename>53.jpg</filename>
	<source>
		<database>Unknown</database>
	</source>
	<size>
		<width>512</width>
		<height>512</height>
		<depth>3</depth>
	</size>
	<segmented>0</segmented>
	<object>
		<name>wangzhihe</name>
		<pose>Unspecified</pose>
		<truncated>0</truncated>
		<difficult>0</difficult>
		<bndbox>
			<xmin>140</xmin>
			<ymin>208</ymin>
			<xmax>364</xmax>
			<ymax>279</ymax>
		</bndbox>
	</object>
</annotation>