<?xml version="1.0" ?><annotation>
	<folder>wangzhihe</folder>
	<filename>84.jpg</filename>
	<source>
		<database>Unknown</database>
	</source>
	<size>
		<width>503</width>
		<height>503</height>
		<depth>3</depth>
	</size>
	<segmented>0</segmented>
	<object>
		<name>wangzhihe</name>
		<pose>Unspecified</pose>
		<truncated>0</truncated>
		<difficult>0</difficult>
		<bndbox>
			<xmin>69</xmin>
			<ymin>227</ymin>
			<xmax>253</xmax>
			<ymax>292</ymax>
		</bndbox>
	</object>
	<object>
		<name>wangzhihe</name>
		<pose>Unspecified</pose>
		<truncated>0</truncated>
		<difficult>0</difficult>
		<bndbox>
			<xmin>264</xmin>
			<ymin>233</ymin>
			<xmax>350</xmax>
			<ymax>293</ymax>
		</bndbox>
	</object>
	<object>
		<name>wangzhihe</name>
		<pose>Unspecified</pose>
		<truncated>0</truncated>
		<difficult>0</difficult>
		<bndbox>
			<xmin>368</xmin>
			<ymin>233</ymin>
			<xmax>449</xmax>
			<ymax>290</ymax>
		</bndbox>
	</object>
</annotation>