<annotation verified="yes">
	<folder>Maestro Dobel</folder>
	<filename>27.jpg</filename>
	<source>
		<database>Unknown</database>
	</source>
	<size>
		<width>375</width>
		<height>485</height>
		<depth>3</depth>
	</size>
	<segmented>0</segmented>
	<object>
		<name>Maestro Dobel</name>
		<pose>Unspecified</pose>
		<truncated>0</truncated>
		<difficult>0</difficult>
		<bndbox>
			<xmin>52</xmin>
			<ymin>227</ymin>
			<xmax>336</xmax>
			<ymax>269</ymax>
		</bndbox>
	</object>
</annotation>
