<?xml version="1.0" ?><annotation verified="yes">
	<folder>VOC2007</folder>
	<filename>40.jpg</filename>
	
	<source>
		<database>Unknown</database>
	</source>
	<size>
		<width>488</width>
		<height>357</height>
		<depth>3</depth>
	</size>
	<segmented>0</segmented>
	<object>
		<name>Hiwatt</name>
		<pose>Unspecified</pose>
		<truncated>0</truncated>
		<difficult>0</difficult>
		<bndbox>
			<xmin>71</xmin>
			<ymin>212</ymin>
			<xmax>140</xmax>
			<ymax>248</ymax>
		</bndbox>
	</object>
	<object>
		<name>Hiwatt</name>
		<pose>Unspecified</pose>
		<truncated>1</truncated>
		<difficult>0</difficult>
		<bndbox>
			<xmin>179</xmin>
			<ymin>2</ymin>
			<xmax>257</xmax>
			<ymax>28</ymax>
		</bndbox>
	</object>
</annotation>