<?xml version="1.0" ?><annotation verified="no">
	<folder>VOC2007</folder>
	<filename>80.jpg</filename>
	
	<source>
		<database>Unknown</database>
	</source>
	<size>
		<width>491</width>
		<height>378</height>
		<depth>3</depth>
	</size>
	<segmented>0</segmented>
	<object>
		<name>popeyes chicken &amp; biscuits</name>
		<pose>Unspecified</pose>
		<truncated>0</truncated>
		<difficult>0</difficult>
		<bndbox>
			<xmin>226</xmin>
			<ymin>224</ymin>
			<xmax>367</xmax>
			<ymax>277</ymax>
		</bndbox>
	</object>
	<object>
		<name>popeyes chicken &amp; biscuits</name>
		<pose>Unspecified</pose>
		<truncated>0</truncated>
		<difficult>0</difficult>
		<bndbox>
			<xmin>428</xmin>
			<ymin>287</ymin>
			<xmax>480</xmax>
			<ymax>359</ymax>
		</bndbox>
	</object>
</annotation>