<?xml version="1.0" ?><annotation>
	<folder>VOC2007</folder>
	<filename>208.jpg</filename>
	
	<source>
		<database>Unknown</database>
	</source>
	<size>
		<width>380</width>
		<height>488</height>
		<depth>1</depth>
	</size>
	<segmented>0</segmented>
	<object>
		<name>ghd</name>
		<pose>Unspecified</pose>
		<truncated>0</truncated>
		<difficult>0</difficult>
		<bndbox>
			<xmin>132</xmin>
			<ymin>315</ymin>
			<xmax>216</xmax>
			<ymax>367</ymax>
		</bndbox>
	</object>
</annotation>