<?xml version="1.0" ?><annotation>
	<folder>adika</folder>
	<filename>54.jpg</filename>
	<source>
		<database>Unknown</database>
	</source>
	<size>
		<width>520</width>
		<height>365</height>
		<depth>3</depth>
	</size>
	<segmented>0</segmented>
	<object>
		<name>adika</name>
		<pose>Unspecified</pose>
		<truncated>1</truncated>
		<difficult>0</difficult>
		<bndbox>
			<xmin>1</xmin>
			<ymin>276</ymin>
			<xmax>520</xmax>
			<ymax>364</ymax>
		</bndbox>
	</object>
</annotation>