<?xml version="1.0" ?><annotation>
	<folder>amish</folder>
	<filename>172.jpg</filename>
	<source>
		<database>Unknown</database>
	</source>
	<size>
		<width>494</width>
		<height>355</height>
		<depth>3</depth>
	</size>
	<segmented>0</segmented>
	<object>
		<name>amish</name>
		<pose>Unspecified</pose>
		<truncated>0</truncated>
		<difficult>0</difficult>
		<bndbox>
			<xmin>6</xmin>
			<ymin>293</ymin>
			<xmax>183</xmax>
			<ymax>352</ymax>
		</bndbox>
	</object>
</annotation>