<?xml version="1.0" ?><annotation verified="no">
	<folder>VOC2007</folder>
	<filename>40.jpg</filename>
	
	<source>
		<database>Unknown</database>
	</source>
	<size>
		<width>493</width>
		<height>362</height>
		<depth>1</depth>
	</size>
	<segmented>0</segmented>
	<object>
		<name>Boulevard</name>
		<pose>Unspecified</pose>
		<truncated>0</truncated>
		<difficult>0</difficult>
		<bndbox>
			<xmin>15</xmin>
			<ymin>276</ymin>
			<xmax>479</xmax>
			<ymax>323</ymax>
		</bndbox>
	</object>
</annotation>