<?xml version="1.0" ?><annotation verified="no">
	<folder>Carling Cider</folder>
	<filename>38.jpg</filename>
	<source>
		<database>Unknown</database>
	</source>
	<size>
		<width>387</width>
		<height>502</height>
		<depth>3</depth>
	</size>
	<segmented>0</segmented>
	<object>
		<name>Carling Cider</name>
		<pose>Unspecified</pose>
		<truncated>0</truncated>
		<difficult>0</difficult>
		<bndbox>
			<xmin>144</xmin>
			<ymin>271</ymin>
			<xmax>264</xmax>
			<ymax>355</ymax>
		</bndbox>
	</object>
</annotation>