<?xml version="1.0" ?><annotation>
	<folder>Bona</folder>
	<filename>59.jpg</filename>
	<source>
		<database>Unknown</database>
	</source>
	<size>
		<width>483</width>
		<height>399</height>
		<depth>3</depth>
	</size>
	<segmented>0</segmented>
	<object>
		<name>Bona</name>
		<pose>Unspecified</pose>
		<truncated>0</truncated>
		<difficult>0</difficult>
		<bndbox>
			<xmin>39</xmin>
			<ymin>15</ymin>
			<xmax>450</xmax>
			<ymax>380</ymax>
		</bndbox>
	</object>
</annotation>