<?xml version="1.0" ?><annotation verified="no">
	<folder>VOC2007</folder>
	<filename>38.jpg</filename>
	
	<source>
		<database>Unknown</database>
	</source>
	<size>
		<width>512</width>
		<height>358</height>
		<depth>3</depth>
	</size>
	<segmented>0</segmented>
	<object>
		<name>meifubao</name>
		<pose>Unspecified</pose>
		<truncated>0</truncated>
		<difficult>0</difficult>
		<bndbox>
			<xmin>64</xmin>
			<ymin>183</ymin>
			<xmax>260</xmax>
			<ymax>234</ymax>
		</bndbox>
	</object>
	<object>
		<name>meifubao</name>
		<pose>Unspecified</pose>
		<truncated>0</truncated>
		<difficult>0</difficult>
		<bndbox>
			<xmin>87</xmin>
			<ymin>79</ymin>
			<xmax>242</xmax>
			<ymax>172</ymax>
		</bndbox>
	</object>
</annotation>