<?xml version="1.0" ?><annotation verified="no">
	<folder>VOC2007</folder>
	<filename>34.jpg</filename>
	
	<source>
		<database>Unknown</database>
	</source>
	<size>
		<width>520</width>
		<height>380</height>
		<depth>3</depth>
	</size>
	<segmented>0</segmented>
	<object>
		<name>Bubbaloo</name>
		<pose>Unspecified</pose>
		<truncated>0</truncated>
		<difficult>0</difficult>
		<bndbox>
			<xmin>71</xmin>
			<ymin>95</ymin>
			<xmax>130</xmax>
			<ymax>182</ymax>
		</bndbox>
	</object>
	<object>
		<name>Bubbaloo</name>
		<pose>Unspecified</pose>
		<truncated>0</truncated>
		<difficult>0</difficult>
		<bndbox>
			<xmin>180</xmin>
			<ymin>100</ymin>
			<xmax>250</xmax>
			<ymax>176</ymax>
		</bndbox>
	</object>
	<object>
		<name>Bubbaloo</name>
		<pose>Unspecified</pose>
		<truncated>0</truncated>
		<difficult>0</difficult>
		<bndbox>
			<xmin>395</xmin>
			<ymin>89</ymin>
			<xmax>465</xmax>
			<ymax>166</ymax>
		</bndbox>
	</object>
	<object>
		<name>Bubbaloo</name>
		<pose>Unspecified</pose>
		<truncated>0</truncated>
		<difficult>0</difficult>
		<bndbox>
			<xmin>288</xmin>
			<ymin>100</ymin>
			<xmax>358</xmax>
			<ymax>176</ymax>
		</bndbox>
	</object>
	<object>
		<name>Bubbaloo</name>
		<pose>Unspecified</pose>
		<truncated>0</truncated>
		<difficult>0</difficult>
		<bndbox>
			<xmin>60</xmin>
			<ymin>203</ymin>
			<xmax>131</xmax>
			<ymax>295</ymax>
		</bndbox>
	</object>
	<object>
		<name>Bubbaloo</name>
		<pose>Unspecified</pose>
		<truncated>0</truncated>
		<difficult>0</difficult>
		<bndbox>
			<xmin>383</xmin>
			<ymin>205</ymin>
			<xmax>454</xmax>
			<ymax>298</ymax>
		</bndbox>
	</object>
	<object>
		<name>Bubbaloo</name>
		<pose>Unspecified</pose>
		<truncated>0</truncated>
		<difficult>0</difficult>
		<bndbox>
			<xmin>284</xmin>
			<ymin>203</ymin>
			<xmax>355</xmax>
			<ymax>295</ymax>
		</bndbox>
	</object>
	<object>
		<name>Bubbaloo</name>
		<pose>Unspecified</pose>
		<truncated>0</truncated>
		<difficult>0</difficult>
		<bndbox>
			<xmin>171</xmin>
			<ymin>197</ymin>
			<xmax>242</xmax>
			<ymax>290</ymax>
		</bndbox>
	</object>
</annotation>