<?xml version="1.0" ?><annotation verified="no">
	<folder>VOC2007</folder>
	<filename>49.jpg</filename>
	
	<source>
		<database>Unknown</database>
	</source>
	<size>
		<width>383</width>
		<height>485</height>
		<depth>3</depth>
	</size>
	<segmented>0</segmented>
	<object>
		<name>Eristoff</name>
		<pose>Unspecified</pose>
		<truncated>0</truncated>
		<difficult>0</difficult>
		<bndbox>
			<xmin>61</xmin>
			<ymin>232</ymin>
			<xmax>278</xmax>
			<ymax>277</ymax>
		</bndbox>
	</object>
</annotation>