<?xml version="1.0" ?><annotation verified="no">
	<folder>jaeger-lecoultre</folder>
	<filename>59.jpg</filename>
	<source>
		<database>Unknown</database>
	</source>
	<size>
		<width>513</width>
		<height>358</height>
		<depth>3</depth>
	</size>
	<segmented>0</segmented>
	<object>
		<name>jaeger-lecoultre</name>
		<pose>Unspecified</pose>
		<truncated>0</truncated>
		<difficult>0</difficult>
		<bndbox>
			<xmin>167</xmin>
			<ymin>48</ymin>
			<xmax>482</xmax>
			<ymax>173</ymax>
		</bndbox>
	</object>
</annotation>