<?xml version="1.0" ?><annotation verified="yes">
	<folder>Boscov's</folder>
	<filename>21.jpg</filename>
	<source>
		<database>Unknown</database>
	</source>
	<size>
		<width>524</width>
		<height>388</height>
		<depth>3</depth>
	</size>
	<segmented>0</segmented>
	<object>
		<name>Boscov's</name>
		<pose>Unspecified</pose>
		<truncated>0</truncated>
		<difficult>0</difficult>
		<bndbox>
			<xmin>183</xmin>
			<ymin>109</ymin>
			<xmax>343</xmax>
			<ymax>196</ymax>
		</bndbox>
	</object>
</annotation>