<annotation verified="no">
	<folder>Medion</folder>
	<filename>23.jpg</filename>
	<source>
		<database>Unknown</database>
	</source>
	<size>
		<width>505</width>
		<height>359</height>
		<depth>3</depth>
	</size>
	<segmented>0</segmented>
	<object>
		<name>Medion</name>
		<pose>Unspecified</pose>
		<truncated>0</truncated>
		<difficult>0</difficult>
		<bndbox>
			<xmin>24</xmin>
			<ymin>123</ymin>
			<xmax>462</xmax>
			<ymax>240</ymax>
		</bndbox>
	</object>
</annotation>
