<annotation verified="no">
	<folder>Medion</folder>
	<filename>37.jpg</filename>
	<source>
		<database>Unknown</database>
	</source>
	<size>
		<width>510</width>
		<height>363</height>
		<depth>3</depth>
	</size>
	<segmented>0</segmented>
	<object>
		<name>Medion</name>
		<pose>Unspecified</pose>
		<truncated>0</truncated>
		<difficult>0</difficult>
		<bndbox>
			<xmin>109</xmin>
			<ymin>88</ymin>
			<xmax>342</xmax>
			<ymax>169</ymax>
		</bndbox>
	</object>
</annotation>
