<annotation verified="no">
	<folder>Medion</folder>
	<filename>46.jpg</filename>
	<source>
		<database>Unknown</database>
	</source>
	<size>
		<width>480</width>
		<height>399</height>
		<depth>3</depth>
	</size>
	<segmented>0</segmented>
	<object>
		<name>Medion</name>
		<pose>Unspecified</pose>
		<truncated>1</truncated>
		<difficult>0</difficult>
		<bndbox>
			<xmin>1</xmin>
			<ymin>119</ymin>
			<xmax>480</xmax>
			<ymax>276</ymax>
		</bndbox>
	</object>
</annotation>
