<?xml version="1.0" ?><annotation verified="no">
	<folder>VOC2007</folder>
	<filename>110.jpg</filename>
	
	<source>
		<database>Unknown</database>
	</source>
	<size>
		<width>490</width>
		<height>394</height>
		<depth>3</depth>
	</size>
	<segmented>0</segmented>
	<object>
		<name>Cibo Espresso</name>
		<pose>Unspecified</pose>
		<truncated>0</truncated>
		<difficult>0</difficult>
		<bndbox>
			<xmin>154</xmin>
			<ymin>160</ymin>
			<xmax>220</xmax>
			<ymax>269</ymax>
		</bndbox>
	</object>
	<object>
		<name>Cibo Espresso</name>
		<pose>Unspecified</pose>
		<truncated>0</truncated>
		<difficult>0</difficult>
		<bndbox>
			<xmin>253</xmin>
			<ymin>195</ymin>
			<xmax>315</xmax>
			<ymax>290</ymax>
		</bndbox>
	</object>
</annotation>