<?xml version="1.0" ?><annotation verified="no">
	<folder>Amoco</folder>
	<filename>33.jpg</filename>
	<source>
		<database>Unknown</database>
	</source>
	<size>
		<width>504</width>
		<height>366</height>
		<depth>3</depth>
	</size>
	<segmented>0</segmented>
	<object>
		<name>Amoco</name>
		<pose>Unspecified</pose>
		<truncated>0</truncated>
		<difficult>0</difficult>
		<bndbox>
			<xmin>11</xmin>
			<ymin>9</ymin>
			<xmax>489</xmax>
			<ymax>358</ymax>
		</bndbox>
	</object>
</annotation>