<?xml version="1.0" ?><annotation verified="no">
	<folder>VOC2007</folder>
	<filename>51.jpg</filename>
	
	<source>
		<database>Unknown</database>
	</source>
	<size>
		<width>512</width>
		<height>398</height>
		<depth>3</depth>
	</size>
	<segmented>0</segmented>
	<object>
		<name>pop mie</name>
		<pose>Unspecified</pose>
		<truncated>0</truncated>
		<difficult>0</difficult>
		<bndbox>
			<xmin>340</xmin>
			<ymin>199</ymin>
			<xmax>434</xmax>
			<ymax>251</ymax>
		</bndbox>
	</object>
	<object>
		<name>pop mie</name>
		<pose>Unspecified</pose>
		<truncated>0</truncated>
		<difficult>0</difficult>
		<bndbox>
			<xmin>176</xmin>
			<ymin>206</ymin>
			<xmax>237</xmax>
			<ymax>240</ymax>
		</bndbox>
	</object>
</annotation>