<?xml version="1.0" ?><annotation verified="yes">
	<folder>VOC2007</folder>
	<filename>3.jpg</filename>
	
	<source>
		<database>Unknown</database>
	</source>
	<size>
		<width>491</width>
		<height>354</height>
		<depth>3</depth>
	</size>
	<segmented>0</segmented>
	<object>
		<name>Ermenegildo Zegna</name>
		<pose>Unspecified</pose>
		<truncated>1</truncated>
		<difficult>0</difficult>
		<bndbox>
			<xmin>2</xmin>
			<ymin>144</ymin>
			<xmax>491</xmax>
			<ymax>223</ymax>
		</bndbox>
	</object>
</annotation>