<annotation verified="yes">
	<folder>Cretacolor</folder>
	<filename>19.jpg</filename>
	<source>
		<database>Unknown</database>
	</source>
	<size>
		<width>523</width>
		<height>354</height>
		<depth>3</depth>
	</size>
	<segmented>0</segmented>
	<object>
		<name>Cretacolor</name>
		<pose>Unspecified</pose>
		<truncated>0</truncated>
		<difficult>0</difficult>
		<bndbox>
			<xmin>22</xmin>
			<ymin>120</ymin>
			<xmax>249</xmax>
			<ymax>199</ymax>
		</bndbox>
	</object>
</annotation>
