<?xml version="1.0" ?><annotation>
	<folder>magnatone</folder>
	<filename>60.jpg</filename>
	<source>
		<database>Unknown</database>
	</source>
	<size>
		<width>516</width>
		<height>398</height>
		<depth>3</depth>
	</size>
	<segmented>0</segmented>
	<object>
		<name>magnatone</name>
		<pose>Unspecified</pose>
		<truncated>0</truncated>
		<difficult>0</difficult>
		<bndbox>
			<xmin>138</xmin>
			<ymin>227</ymin>
			<xmax>279</xmax>
			<ymax>252</ymax>
		</bndbox>
	</object>
</annotation>