<?xml version="1.0" ?><annotation verified="yes">
	<folder>rickard's white</folder>
	<filename>27.jpg</filename>
	<source>
		<database>Unknown</database>
	</source>
	<size>
		<width>518</width>
		<height>518</height>
		<depth>3</depth>
	</size>
	<segmented>0</segmented>
	<object>
		<name>rickard's white</name>
		<pose>Unspecified</pose>
		<truncated>0</truncated>
		<difficult>0</difficult>
		<bndbox>
			<xmin>153</xmin>
			<ymin>258</ymin>
			<xmax>375</xmax>
			<ymax>479</ymax>
		</bndbox>
	</object>
</annotation>