<?xml version="1.0" ?><annotation verified="no">
	<folder>wildcountry</folder>
	<filename>28.jpg</filename>
	<source>
		<database>Unknown</database>
	</source>
	<size>
		<width>506</width>
		<height>360</height>
		<depth>1</depth>
	</size>
	<segmented>0</segmented>
	<object>
		<name>wildcountry</name>
		<pose>Unspecified</pose>
		<truncated>0</truncated>
		<difficult>0</difficult>
		<bndbox>
			<xmin>21</xmin>
			<ymin>8</ymin>
			<xmax>294</xmax>
			<ymax>323</ymax>
		</bndbox>
	</object>
	<object>
		<name>wildcountry</name>
		<pose>Unspecified</pose>
		<truncated>0</truncated>
		<difficult>0</difficult>
		<bndbox>
			<xmin>305</xmin>
			<ymin>20</ymin>
			<xmax>405</xmax>
			<ymax>329</ymax>
		</bndbox>
	</object>
</annotation>