<?xml version="1.0" ?><annotation verified="no">
	<folder>wolf brand chili</folder>
	<filename>14.jpg</filename>
	<source>
		<database>Unknown</database>
	</source>
	<size>
		<width>490</width>
		<height>367</height>
		<depth>3</depth>
	</size>
	<segmented>0</segmented>
	<object>
		<name>wolf brand chili</name>
		<pose>Unspecified</pose>
		<truncated>0</truncated>
		<difficult>0</difficult>
		<bndbox>
			<xmin>60</xmin>
			<ymin>78</ymin>
			<xmax>214</xmax>
			<ymax>197</ymax>
		</bndbox>
	</object>
	<object>
		<name>wolf brand chili</name>
		<pose>Unspecified</pose>
		<truncated>0</truncated>
		<difficult>0</difficult>
		<bndbox>
			<xmin>279</xmin>
			<ymin>85</ymin>
			<xmax>444</xmax>
			<ymax>217</ymax>
		</bndbox>
	</object>
</annotation>