<?xml version="1.0" ?><annotation verified="no">
	<folder>VOC2007</folder>
	<filename>3.jpg</filename>
	
	<source>
		<database>Unknown</database>
	</source>
	<size>
		<width>396</width>
		<height>518</height>
		<depth>3</depth>
	</size>
	<segmented>0</segmented>
	<object>
		<name>mido</name>
		<pose>Unspecified</pose>
		<truncated>0</truncated>
		<difficult>0</difficult>
		<bndbox>
			<xmin>177</xmin>
			<ymin>177</ymin>
			<xmax>222</xmax>
			<ymax>190</ymax>
		</bndbox>
	</object>
</annotation>