<annotation verified="yes">
	<folder>KTM</folder>
	<filename>44.jpg</filename>
	<source>
		<database>Unknown</database>
	</source>
	<size>
		<width>499</width>
		<height>378</height>
		<depth>3</depth>
	</size>
	<segmented>0</segmented>
	<object>
		<name>KTM</name>
		<pose>Unspecified</pose>
		<truncated>1</truncated>
		<difficult>0</difficult>
		<bndbox>
			<xmin>204</xmin>
			<ymin>194</ymin>
			<xmax>499</xmax>
			<ymax>322</ymax>
		</bndbox>
	</object>
</annotation>
