<annotation verified="yes">
	<folder>Maker's Mark</folder>
	<filename>54.jpg</filename>
	<source>
		<database>Unknown</database>
	</source>
	<size>
		<width>485</width>
		<height>394</height>
		<depth>3</depth>
	</size>
	<segmented>0</segmented>
	<object>
		<name>Maker's Mark</name>
		<pose>Unspecified</pose>
		<truncated>1</truncated>
		<difficult>0</difficult>
		<bndbox>
			<xmin>313</xmin>
			<ymin>126</ymin>
			<xmax>466</xmax>
			<ymax>394</ymax>
		</bndbox>
	</object>
</annotation>
