<?xml version="1.0" ?><annotation verified="yes">
	<folder>VOC2007</folder>
	<filename>88.jpg</filename>
	
	<source>
		<database>Unknown</database>
	</source>
	<size>
		<width>360</width>
		<height>511</height>
		<depth>3</depth>
	</size>
	<segmented>0</segmented>
	<object>
		<name>Alfani</name>
		<pose>Unspecified</pose>
		<truncated>0</truncated>
		<difficult>0</difficult>
		<bndbox>
			<xmin>111</xmin>
			<ymin>222</ymin>
			<xmax>248</xmax>
			<ymax>268</ymax>
		</bndbox>
	</object>
</annotation>