<?xml version="1.0" ?><annotation verified="yes">
	<folder>VOC2007</folder>
	<filename>66.jpg</filename>
	
	<source>
		<database>Unknown</database>
	</source>
	<size>
		<width>495</width>
		<height>356</height>
		<depth>3</depth>
	</size>
	<segmented>0</segmented>
	<object>
		<name>HOM</name>
		<pose>Unspecified</pose>
		<truncated>0</truncated>
		<difficult>0</difficult>
		<bndbox>
			<xmin>48</xmin>
			<ymin>129</ymin>
			<xmax>462</xmax>
			<ymax>223</ymax>
		</bndbox>
	</object>
</annotation>