<?xml version="1.0" ?><annotation verified="no">
	<folder>huarun</folder>
	<filename>178.jpg</filename>
	<source>
		<database>Unknown</database>
	</source>
	<size>
		<width>496</width>
		<height>351</height>
		<depth>3</depth>
	</size>
	<segmented>0</segmented>
	<object>
		<name>huarun</name>
		<pose>Unspecified</pose>
		<truncated>0</truncated>
		<difficult>0</difficult>
		<bndbox>
			<xmin>45</xmin>
			<ymin>29</ymin>
			<xmax>93</xmax>
			<ymax>66</ymax>
		</bndbox>
	</object>
</annotation>