<?xml version="1.0" ?><annotation verified="no">
	<folder>VOC2007</folder>
	<filename>4.jpg</filename>
	
	<source>
		<database>Unknown</database>
	</source>
	<size>
		<width>361</width>
		<height>488</height>
		<depth>1</depth>
	</size>
	<segmented>0</segmented>
	<object>
		<name>Berghaus</name>
		<pose>Unspecified</pose>
		<truncated>0</truncated>
		<difficult>0</difficult>
		<bndbox>
			<xmin>16</xmin>
			<ymin>307</ymin>
			<xmax>339</xmax>
			<ymax>432</ymax>
		</bndbox>
	</object>
	<object>
		<name>Berghaus</name>
		<pose>Unspecified</pose>
		<truncated>0</truncated>
		<difficult>0</difficult>
		<bndbox>
			<xmin>8</xmin>
			<ymin>58</ymin>
			<xmax>348</xmax>
			<ymax>182</ymax>
		</bndbox>
	</object>
</annotation>