<?xml version="1.0" ?><annotation verified="no">
	<folder>petro-canada</folder>
	<filename>107.jpg</filename>
	<source>
		<database>Unknown</database>
	</source>
	<size>
		<width>371</width>
		<height>519</height>
		<depth>3</depth>
	</size>
	<segmented>0</segmented>
	<object>
		<name>petro-canada</name>
		<pose>Unspecified</pose>
		<truncated>0</truncated>
		<difficult>0</difficult>
		<bndbox>
			<xmin>59</xmin>
			<ymin>155</ymin>
			<xmax>326</xmax>
			<ymax>217</ymax>
		</bndbox>
	</object>
</annotation>