<?xml version="1.0" ?><annotation verified="yes">
	<folder>ready brek</folder>
	<filename>93.jpg</filename>
	<source>
		<database>Unknown</database>
	</source>
	<size>
		<width>361</width>
		<height>522</height>
		<depth>3</depth>
	</size>
	<segmented>0</segmented>
	<object>
		<name>ready brek</name>
		<pose>Unspecified</pose>
		<truncated>0</truncated>
		<difficult>0</difficult>
		<bndbox>
			<xmin>44</xmin>
			<ymin>112</ymin>
			<xmax>337</xmax>
			<ymax>317</ymax>
		</bndbox>
	</object>
</annotation>