<?xml version="1.0" ?><annotation verified="no">
	<folder>huarun</folder>
	<filename>174.jpg</filename>
	<source>
		<database>Unknown</database>
	</source>
	<size>
		<width>493</width>
		<height>371</height>
		<depth>3</depth>
	</size>
	<segmented>0</segmented>
	<object>
		<name>huarun</name>
		<pose>Unspecified</pose>
		<truncated>0</truncated>
		<difficult>0</difficult>
		<bndbox>
			<xmin>193</xmin>
			<ymin>179</ymin>
			<xmax>256</xmax>
			<ymax>201</ymax>
		</bndbox>
	</object>
</annotation>