<?xml version="1.0" ?><annotation>
	<folder>biotene</folder>
	<filename>106.jpg</filename>
	<source>
		<database>Unknown</database>
	</source>
	<size>
		<width>492</width>
		<height>372</height>
		<depth>3</depth>
	</size>
	<segmented>0</segmented>
	<object>
		<name>biotene</name>
		<pose>Unspecified</pose>
		<truncated>0</truncated>
		<difficult>0</difficult>
		<bndbox>
			<xmin>209</xmin>
			<ymin>132</ymin>
			<xmax>282</xmax>
			<ymax>189</ymax>
		</bndbox>
	</object>
</annotation>