<annotation verified="no">
	<folder>Chiclets</folder>
	<filename>10.jpg</filename>
	<source>
		<database>Unknown</database>
	</source>
	<size>
		<width>503</width>
		<height>379</height>
		<depth>3</depth>
	</size>
	<segmented>0</segmented>
	<object>
		<name>Chiclets</name>
		<pose>Unspecified</pose>
		<truncated>0</truncated>
		<difficult>0</difficult>
		<bndbox>
			<xmin>168</xmin>
			<ymin>140</ymin>
			<xmax>420</xmax>
			<ymax>228</ymax>
		</bndbox>
	</object>
</annotation>
