<annotation verified="no">
	<folder>Everlast</folder>
	<filename>53.jpg</filename>
	<source>
		<database>Unknown</database>
	</source>
	<size>
		<width>508</width>
		<height>354</height>
		<depth>3</depth>
	</size>
	<segmented>0</segmented>
	<object>
		<name>Everlast</name>
		<pose>Unspecified</pose>
		<truncated>0</truncated>
		<difficult>0</difficult>
		<bndbox>
			<xmin>177</xmin>
			<ymin>86</ymin>
			<xmax>347</xmax>
			<ymax>178</ymax>
		</bndbox>
	</object>
</annotation>
