<?xml version="1.0" ?><annotation>
	<folder>VOC2007</folder>
	<filename>11.jpg</filename>
	
	<source>
		<database>Unknown</database>
	</source>
	<size>
		<width>481</width>
		<height>373</height>
		<depth>3</depth>
	</size>
	<segmented>0</segmented>
	<object>
		<name>maidenform</name>
		<pose>Unspecified</pose>
		<truncated>1</truncated>
		<difficult>0</difficult>
		<bndbox>
			<xmin>48</xmin>
			<ymin>185</ymin>
			<xmax>481</xmax>
			<ymax>249</ymax>
		</bndbox>
	</object>
</annotation>