<?xml version="1.0" ?><annotation verified="no">
	<folder>Caparo</folder>
	<filename>17.jpg</filename>
	<source>
		<database>Unknown</database>
	</source>
	<size>
		<width>484</width>
		<height>383</height>
		<depth>1</depth>
	</size>
	<segmented>0</segmented>
	<object>
		<name>Caparo</name>
		<pose>Unspecified</pose>
		<truncated>0</truncated>
		<difficult>0</difficult>
		<bndbox>
			<xmin>11</xmin>
			<ymin>19</ymin>
			<xmax>479</xmax>
			<ymax>256</ymax>
		</bndbox>
	</object>
</annotation>