<annotation verified="yes">
	<folder>Hershey's Cookies 'n' Creme</folder>
	<filename>52.jpg</filename>
	<source>
		<database>Unknown</database>
	</source>
	<size>
		<width>364</width>
		<height>487</height>
		<depth>3</depth>
	</size>
	<segmented>0</segmented>
	<object>
		<name>Hershey's Cookies 'n' Creme</name>
		<pose>Unspecified</pose>
		<truncated>0</truncated>
		<difficult>0</difficult>
		<bndbox>
			<xmin>56</xmin>
			<ymin>171</ymin>
			<xmax>296</xmax>
			<ymax>370</ymax>
		</bndbox>
	</object>
</annotation>
