<?xml version="1.0" ?><annotation verified="no">
	<folder>whisper</folder>
	<filename>18.jpg</filename>
	<source>
		<database>Unknown</database>
	</source>
	<size>
		<width>503</width>
		<height>503</height>
		<depth>3</depth>
	</size>
	<segmented>0</segmented>
	<object>
		<name>whisper</name>
		<pose>Unspecified</pose>
		<truncated>0</truncated>
		<difficult>0</difficult>
		<bndbox>
			<xmin>23</xmin>
			<ymin>10</ymin>
			<xmax>64</xmax>
			<ymax>24</ymax>
		</bndbox>
	</object>
</annotation>