<annotation verified="no">
	<folder>chando</folder>
	<filename>39.jpg</filename>
	<source>
		<database>Unknown</database>
	</source>
	<size>
		<width>393</width>
		<height>521</height>
		<depth>3</depth>
	</size>
	<segmented>0</segmented>
	<object>
		<name>chando</name>
		<pose>Unspecified</pose>
		<truncated>0</truncated>
		<difficult>0</difficult>
		<bndbox>
			<xmin>2</xmin>
			<ymin>171</ymin>
			<xmax>387</xmax>
			<ymax>327</ymax>
		</bndbox>
	</object>
</annotation>
