<annotation verified="no">
	<folder>cheesecake factory</folder>
	<filename>91.jpg</filename>
	<source>
		<database>Unknown</database>
	</source>
	<size>
		<width>494</width>
		<height>393</height>
		<depth>3</depth>
	</size>
	<segmented>0</segmented>
	<object>
		<name>cheesecake factory</name>
		<pose>Unspecified</pose>
		<truncated>0</truncated>
		<difficult>0</difficult>
		<bndbox>
			<xmin>46</xmin>
			<ymin>72</ymin>
			<xmax>129</xmax>
			<ymax>125</ymax>
		</bndbox>
	</object>
	<object>
		<name>cheesecake factory</name>
		<pose>Unspecified</pose>
		<truncated>0</truncated>
		<difficult>0</difficult>
		<bndbox>
			<xmin>201</xmin>
			<ymin>56</ymin>
			<xmax>289</xmax>
			<ymax>114</ymax>
		</bndbox>
	</object>
	<object>
		<name>cheesecake factory</name>
		<pose>Unspecified</pose>
		<truncated>0</truncated>
		<difficult>0</difficult>
		<bndbox>
			<xmin>364</xmin>
			<ymin>72</ymin>
			<xmax>448</xmax>
			<ymax>124</ymax>
		</bndbox>
	</object>
</annotation>
