<?xml version="1.0" ?><annotation>
	<folder>band-aid</folder>
	<filename>9.jpg</filename>
	<source>
		<database>Unknown</database>
	</source>
	<size>
		<width>505</width>
		<height>354</height>
		<depth>3</depth>
	</size>
	<segmented>0</segmented>
	<object>
		<name>band-aid</name>
		<pose>Unspecified</pose>
		<truncated>0</truncated>
		<difficult>0</difficult>
		<bndbox>
			<xmin>25</xmin>
			<ymin>109</ymin>
			<xmax>493</xmax>
			<ymax>331</ymax>
		</bndbox>
	</object>
</annotation>