<annotation verified="no">
	<folder>Marussia</folder>
	<filename>32.jpg</filename>
	<source>
		<database>Unknown</database>
	</source>
	<size>
		<width>523</width>
		<height>357</height>
		<depth>3</depth>
	</size>
	<segmented>0</segmented>
	<object>
		<name>Marussia</name>
		<pose>Unspecified</pose>
		<truncated>0</truncated>
		<difficult>0</difficult>
		<bndbox>
			<xmin>222</xmin>
			<ymin>121</ymin>
			<xmax>395</xmax>
			<ymax>271</ymax>
		</bndbox>
	</object>
	<object>
		<name>Marussia</name>
		<pose>Unspecified</pose>
		<truncated>1</truncated>
		<difficult>0</difficult>
		<bndbox>
			<xmin>1</xmin>
			<ymin>4</ymin>
			<xmax>406</xmax>
			<ymax>205</ymax>
		</bndbox>
	</object>
</annotation>
