<?xml version="1.0" ?><annotation verified="yes">
	<folder>razzle dazzle rice krispies</folder>
	<filename>42.jpg</filename>
	<source>
		<database>Unknown</database>
	</source>
	<size>
		<width>497</width>
		<height>372</height>
		<depth>3</depth>
	</size>
	<segmented>0</segmented>
	<object>
		<name>razzle dazzle rice krispies</name>
		<pose>Unspecified</pose>
		<truncated>0</truncated>
		<difficult>0</difficult>
		<bndbox>
			<xmin>124</xmin>
			<ymin>5</ymin>
			<xmax>396</xmax>
			<ymax>157</ymax>
		</bndbox>
	</object>
</annotation>