<?xml version="1.0" ?><annotation>
	<folder>VOC2007</folder>
	<filename>59.jpg</filename>
	
	<source>
		<database>Unknown</database>
	</source>
	<size>
		<width>383</width>
		<height>500</height>
		<depth>3</depth>
	</size>
	<segmented>0</segmented>
	<object>
		<name>girard-perregaux</name>
		<pose>Unspecified</pose>
		<truncated>0</truncated>
		<difficult>0</difficult>
		<bndbox>
			<xmin>92</xmin>
			<ymin>92</ymin>
			<xmax>302</xmax>
			<ymax>146</ymax>
		</bndbox>
	</object>
	<object>
		<name>girard-perregaux</name>
		<pose>Unspecified</pose>
		<truncated>0</truncated>
		<difficult>0</difficult>
		<bndbox>
			<xmin>193</xmin>
			<ymin>349</ymin>
			<xmax>340</xmax>
			<ymax>387</ymax>
		</bndbox>
	</object>
</annotation>