<?xml version="1.0" ?><annotation verified="no">
	<folder>VOC2007</folder>
	<filename>6.jpg</filename>
	
	<source>
		<database>Unknown</database>
	</source>
	<size>
		<width>518</width>
		<height>389</height>
		<depth>1</depth>
	</size>
	<segmented>0</segmented>
	<object>
		<name>Biotherm</name>
		<pose>Unspecified</pose>
		<truncated>0</truncated>
		<difficult>0</difficult>
		<bndbox>
			<xmin>13</xmin>
			<ymin>42</ymin>
			<xmax>203</xmax>
			<ymax>147</ymax>
		</bndbox>
	</object>
	<object>
		<name>Biotherm</name>
		<pose>Unspecified</pose>
		<truncated>0</truncated>
		<difficult>0</difficult>
		<bndbox>
			<xmin>17</xmin>
			<ymin>157</ymin>
			<xmax>203</xmax>
			<ymax>357</ymax>
		</bndbox>
	</object>
</annotation>