<annotation verified="yes">
	<folder>Hooters</folder>
	<filename>33.jpg</filename>
	<source>
		<database>Unknown</database>
	</source>
	<size>
		<width>490</width>
		<height>362</height>
		<depth>3</depth>
	</size>
	<segmented>0</segmented>
	<object>
		<name>Hooters</name>
		<pose>Unspecified</pose>
		<truncated>0</truncated>
		<difficult>0</difficult>
		<bndbox>
			<xmin>54</xmin>
			<ymin>96</ymin>
			<xmax>455</xmax>
			<ymax>193</ymax>
		</bndbox>
	</object>
</annotation>
