<?xml version="1.0" ?><annotation>
	<folder>VOC2007</folder>
	<filename>183.jpg</filename>
	
	<source>
		<database>Unknown</database>
	</source>
	<size>
		<width>396</width>
		<height>496</height>
		<depth>3</depth>
	</size>
	<segmented>0</segmented>
	<object>
		<name>Jus-Rol</name>
		<pose>Unspecified</pose>
		<truncated>0</truncated>
		<difficult>0</difficult>
		<bndbox>
			<xmin>12</xmin>
			<ymin>34</ymin>
			<xmax>109</xmax>
			<ymax>57</ymax>
		</bndbox>
	</object>
	<object>
		<name>Jus-Rol</name>
		<pose>Unspecified</pose>
		<truncated>0</truncated>
		<difficult>0</difficult>
		<bndbox>
			<xmin>281</xmin>
			<ymin>439</ymin>
			<xmax>331</xmax>
			<ymax>456</ymax>
		</bndbox>
	</object>
	<object>
		<name>Jus-Rol</name>
		<pose>Unspecified</pose>
		<truncated>0</truncated>
		<difficult>0</difficult>
		<bndbox>
			<xmin>262</xmin>
			<ymin>465</ymin>
			<xmax>320</xmax>
			<ymax>485</ymax>
		</bndbox>
	</object>
</annotation>