<?xml version="1.0" ?><annotation verified="no">
	<folder>lego mindstorms nxt</folder>
	<filename>19.jpg</filename>
	<source>
		<database>Unknown</database>
	</source>
	<size>
		<width>481</width>
		<height>360</height>
		<depth>3</depth>
	</size>
	<segmented>0</segmented>
	<object>
		<name>lego mindstorms nxt</name>
		<pose>Unspecified</pose>
		<truncated>0</truncated>
		<difficult>0</difficult>
		<bndbox>
			<xmin>139</xmin>
			<ymin>97</ymin>
			<xmax>334</xmax>
			<ymax>187</ymax>
		</bndbox>
	</object>
</annotation>