<?xml version="1.0" ?><annotation>
	<folder>3t cycling</folder>
	<filename>77.jpg</filename>
	<source>
		<database>Unknown</database>
	</source>
	<size>
		<width>356</width>
		<height>488</height>
		<depth>3</depth>
	</size>
	<segmented>0</segmented>
	<object>
		<name>3t cycling</name>
		<pose>Unspecified</pose>
		<truncated>0</truncated>
		<difficult>0</difficult>
		<bndbox>
			<xmin>21</xmin>
			<ymin>15</ymin>
			<xmax>76</xmax>
			<ymax>78</ymax>
		</bndbox>
	</object>
</annotation>