<?xml version="1.0" ?><annotation verified="no">
	<folder>VOC2007</folder>
	<filename>159.jpg</filename>
	
	<source>
		<database>Unknown</database>
	</source>
	<size>
		<width>492</width>
		<height>357</height>
		<depth>3</depth>
	</size>
	<segmented>0</segmented>
	<object>
		<name>chewits</name>
		<pose>Unspecified</pose>
		<truncated>0</truncated>
		<difficult>0</difficult>
		<bndbox>
			<xmin>185</xmin>
			<ymin>56</ymin>
			<xmax>435</xmax>
			<ymax>225</ymax>
		</bndbox>
	</object>
</annotation>