<?xml version="1.0" ?><annotation verified="no">
	<folder>reusch</folder>
	<filename>61.jpg</filename>
	<source>
		<database>Unknown</database>
	</source>
	<size>
		<width>503</width>
		<height>341</height>
		<depth>3</depth>
	</size>
	<segmented>0</segmented>
	<object>
		<name>reusch</name>
		<pose>Unspecified</pose>
		<truncated>0</truncated>
		<difficult>0</difficult>
		<bndbox>
			<xmin>85</xmin>
			<ymin>118</ymin>
			<xmax>418</xmax>
			<ymax>214</ymax>
		</bndbox>
	</object>
</annotation>