<?xml version="1.0" ?><annotation verified="no">
	<folder>VOC2007</folder>
	<filename>30.jpg</filename>
	
	<source>
		<database>Unknown</database>
	</source>
	<size>
		<width>524</width>
		<height>350</height>
		<depth>3</depth>
	</size>
	<segmented>0</segmented>
	<object>
		<name>Fruit2O</name>
		<pose>Unspecified</pose>
		<truncated>0</truncated>
		<difficult>0</difficult>
		<bndbox>
			<xmin>189</xmin>
			<ymin>141</ymin>
			<xmax>235</xmax>
			<ymax>165</ymax>
		</bndbox>
	</object>
	<object>
		<name>Fruit2O</name>
		<pose>Unspecified</pose>
		<truncated>0</truncated>
		<difficult>0</difficult>
		<bndbox>
			<xmin>279</xmin>
			<ymin>139</ymin>
			<xmax>336</xmax>
			<ymax>163</ymax>
		</bndbox>
	</object>
	<object>
		<name>Fruit2O</name>
		<pose>Unspecified</pose>
		<truncated>0</truncated>
		<difficult>0</difficult>
		<bndbox>
			<xmin>359</xmin>
			<ymin>147</ymin>
			<xmax>406</xmax>
			<ymax>169</ymax>
		</bndbox>
	</object>
	<object>
		<name>Fruit2O</name>
		<pose>Unspecified</pose>
		<truncated>0</truncated>
		<difficult>0</difficult>
		<bndbox>
			<xmin>439</xmin>
			<ymin>143</ymin>
			<xmax>494</xmax>
			<ymax>165</ymax>
		</bndbox>
	</object>
	<object>
		<name>Fruit2O</name>
		<pose>Unspecified</pose>
		<truncated>0</truncated>
		<difficult>0</difficult>
		<bndbox>
			<xmin>90</xmin>
			<ymin>139</ymin>
			<xmax>153</xmax>
			<ymax>165</ymax>
		</bndbox>
	</object>
	<object>
		<name>Fruit2O</name>
		<pose>Unspecified</pose>
		<truncated>0</truncated>
		<difficult>0</difficult>
		<bndbox>
			<xmin>18</xmin>
			<ymin>145</ymin>
			<xmax>71</xmax>
			<ymax>167</ymax>
		</bndbox>
	</object>
</annotation>