<?xml version="1.0" ?><annotation>
	<folder>VOC2007</folder>
	<filename>70.jpg</filename>
	
	<source>
		<database>Unknown</database>
	</source>
	<size>
		<width>396</width>
		<height>485</height>
		<depth>3</depth>
	</size>
	<segmented>0</segmented>
	<object>
		<name>yong master</name>
		<pose>Unspecified</pose>
		<truncated>0</truncated>
		<difficult>0</difficult>
		<bndbox>
			<xmin>131</xmin>
			<ymin>6</ymin>
			<xmax>268</xmax>
			<ymax>72</ymax>
		</bndbox>
	</object>
	<object>
		<name>yong master</name>
		<pose>Unspecified</pose>
		<truncated>0</truncated>
		<difficult>0</difficult>
		<bndbox>
			<xmin>85</xmin>
			<ymin>288</ymin>
			<xmax>137</xmax>
			<ymax>310</ymax>
		</bndbox>
	</object>
</annotation>