<?xml version="1.0" ?><annotation>
	<folder>VOC2007</folder>
	<filename>82.jpg</filename>
	
	<source>
		<database>Unknown</database>
	</source>
	<size>
		<width>518</width>
		<height>372</height>
		<depth>3</depth>
	</size>
	<segmented>0</segmented>
	<object>
		<name>pisen</name>
		<pose>Unspecified</pose>
		<truncated>0</truncated>
		<difficult>0</difficult>
		<bndbox>
			<xmin>43</xmin>
			<ymin>68</ymin>
			<xmax>70</xmax>
			<ymax>257</ymax>
		</bndbox>
	</object>
	<object>
		<name>pisen</name>
		<pose>Unspecified</pose>
		<truncated>0</truncated>
		<difficult>0</difficult>
		<bndbox>
			<xmin>177</xmin>
			<ymin>124</ymin>
			<xmax>452</xmax>
			<ymax>183</ymax>
		</bndbox>
	</object>
	<object>
		<name>pisen</name>
		<pose>Unspecified</pose>
		<truncated>0</truncated>
		<difficult>0</difficult>
		<bndbox>
			<xmin>116</xmin>
			<ymin>331</ymin>
			<xmax>171</xmax>
			<ymax>345</ymax>
		</bndbox>
	</object>
	<object>
		<name>pisen</name>
		<pose>Unspecified</pose>
		<truncated>0</truncated>
		<difficult>0</difficult>
		<bndbox>
			<xmin>340</xmin>
			<ymin>331</ymin>
			<xmax>396</xmax>
			<ymax>347</ymax>
		</bndbox>
	</object>
</annotation>