<annotation verified="no">
	<folder>Maxwell House</folder>
	<filename>17.jpg</filename>
	<source>
		<database>Unknown</database>
	</source>
	<size>
		<width>491</width>
		<height>396</height>
		<depth>3</depth>
	</size>
	<segmented>0</segmented>
	<object>
		<name>Maxwell House</name>
		<pose>Unspecified</pose>
		<truncated>0</truncated>
		<difficult>0</difficult>
		<bndbox>
			<xmin>49</xmin>
			<ymin>107</ymin>
			<xmax>456</xmax>
			<ymax>357</ymax>
		</bndbox>
	</object>
</annotation>
