<?xml version="1.0" ?><annotation verified="no">
	<folder>wienerschnitzel</folder>
	<filename>87.jpg</filename>
	<source>
		<database>Unknown</database>
	</source>
	<size>
		<width>494</width>
		<height>360</height>
		<depth>3</depth>
	</size>
	<segmented>0</segmented>
	<object>
		<name>wienerschnitzel</name>
		<pose>Unspecified</pose>
		<truncated>0</truncated>
		<difficult>0</difficult>
		<bndbox>
			<xmin>191</xmin>
			<ymin>125</ymin>
			<xmax>305</xmax>
			<ymax>231</ymax>
		</bndbox>
	</object>
</annotation>