<?xml version="1.0" ?><annotation>
	<folder>VOC2007</folder>
	<filename>16.jpg</filename>
	
	<source>
		<database>Unknown</database>
	</source>
	<size>
		<width>375</width>
		<height>503</height>
		<depth>3</depth>
	</size>
	<segmented>0</segmented>
	<object>
		<name>luciano soprani</name>
		<pose>Unspecified</pose>
		<truncated>0</truncated>
		<difficult>0</difficult>
		<bndbox>
			<xmin>42</xmin>
			<ymin>267</ymin>
			<xmax>205</xmax>
			<ymax>365</ymax>
		</bndbox>
	</object>
	<object>
		<name>luciano soprani</name>
		<pose>Unspecified</pose>
		<truncated>0</truncated>
		<difficult>0</difficult>
		<bndbox>
			<xmin>261</xmin>
			<ymin>333</ymin>
			<xmax>319</xmax>
			<ymax>375</ymax>
		</bndbox>
	</object>
</annotation>