<annotation verified="yes">
	<folder>tudor</folder>
	<filename>27.jpg</filename>
	<source>
		<database>Unknown</database>
	</source>
	<size>
		<width>513</width>
		<height>353</height>
		<depth>3</depth>
	</size>
	<segmented>0</segmented>
	<object>
		<name>tudor</name>
		<pose>Unspecified</pose>
		<truncated>0</truncated>
		<difficult>0</difficult>
		<bndbox>
			<xmin>265</xmin>
			<ymin>107</ymin>
			<xmax>334</xmax>
			<ymax>189</ymax>
		</bndbox>
	</object>
</annotation>
