<annotation verified="yes">
	<folder>Hunt's Snack Pack</folder>
	<filename>42.jpg</filename>
	<source>
		<database>Unknown</database>
	</source>
	<size>
		<width>524</width>
		<height>379</height>
		<depth>3</depth>
	</size>
	<segmented>0</segmented>
	<object>
		<name>Hunt's Snack Pack</name>
		<pose>Unspecified</pose>
		<truncated>0</truncated>
		<difficult>0</difficult>
		<bndbox>
			<xmin>136</xmin>
			<ymin>87</ymin>
			<xmax>280</xmax>
			<ymax>188</ymax>
		</bndbox>
	</object>
</annotation>
