<annotation verified="yes">
	<folder>Hunt's Snack Pack</folder>
	<filename>65.jpg</filename>
	<source>
		<database>Unknown</database>
	</source>
	<size>
		<width>492</width>
		<height>374</height>
		<depth>3</depth>
	</size>
	<segmented>0</segmented>
	<object>
		<name>Hunt's Snack Pack</name>
		<pose>Unspecified</pose>
		<truncated>0</truncated>
		<difficult>0</difficult>
		<bndbox>
			<xmin>124</xmin>
			<ymin>10</ymin>
			<xmax>278</xmax>
			<ymax>99</ymax>
		</bndbox>
	</object>
	<object>
		<name>Hunt's Snack Pack</name>
		<pose>Unspecified</pose>
		<truncated>0</truncated>
		<difficult>0</difficult>
		<bndbox>
			<xmin>250</xmin>
			<ymin>190</ymin>
			<xmax>405</xmax>
			<ymax>289</ymax>
		</bndbox>
	</object>
	<object>
		<name>Hunt's Snack Pack</name>
		<pose>Unspecified</pose>
		<truncated>0</truncated>
		<difficult>0</difficult>
		<bndbox>
			<xmin>5</xmin>
			<ymin>187</ymin>
			<xmax>147</xmax>
			<ymax>288</ymax>
		</bndbox>
	</object>
</annotation>
