<annotation>
	<folder>Hunt's Snack Pack</folder>
	<filename>78.jpg</filename>
	<source>
		<database>Unknown</database>
	</source>
	<size>
		<width>483</width>
		<height>359</height>
		<depth>3</depth>
	</size>
	<segmented>0</segmented>
	<object>
		<name>Hunt's Snack Pack</name>
		<pose>Unspecified</pose>
		<truncated>0</truncated>
		<difficult>0</difficult>
		<bndbox>
			<xmin>161</xmin>
			<ymin>15</ymin>
			<xmax>284</xmax>
			<ymax>76</ymax>
		</bndbox>
	</object>
	<object>
		<name>Hunt's Snack Pack</name>
		<pose>Unspecified</pose>
		<truncated>0</truncated>
		<difficult>0</difficult>
		<bndbox>
			<xmin>252</xmin>
			<ymin>176</ymin>
			<xmax>368</xmax>
			<ymax>235</ymax>
		</bndbox>
	</object>
	<object>
		<name>Hunt's Snack Pack</name>
		<pose>Unspecified</pose>
		<truncated>0</truncated>
		<difficult>0</difficult>
		<bndbox>
			<xmin>253</xmin>
			<ymin>283</ymin>
			<xmax>357</xmax>
			<ymax>332</ymax>
		</bndbox>
	</object>
	<object>
		<name>Hunt's Snack Pack</name>
		<pose>Unspecified</pose>
		<truncated>0</truncated>
		<difficult>0</difficult>
		<bndbox>
			<xmin>73</xmin>
			<ymin>162</ymin>
			<xmax>181</xmax>
			<ymax>230</ymax>
		</bndbox>
	</object>
	<object>
		<name>Hunt's Snack Pack</name>
		<pose>Unspecified</pose>
		<truncated>0</truncated>
		<difficult>0</difficult>
		<bndbox>
			<xmin>107</xmin>
			<ymin>276</ymin>
			<xmax>208</xmax>
			<ymax>335</ymax>
		</bndbox>
	</object>
</annotation>
