<?xml version="1.0" ?><annotation>
	<folder>VOC2007</folder>
	<filename>34.jpg</filename>
	
	<source>
		<database>Unknown</database>
	</source>
	<size>
		<width>500</width>
		<height>360</height>
		<depth>1</depth>
	</size>
	<segmented>0</segmented>
	<object>
		<name>marchesa</name>
		<pose>Unspecified</pose>
		<truncated>0</truncated>
		<difficult>0</difficult>
		<bndbox>
			<xmin>9</xmin>
			<ymin>122</ymin>
			<xmax>487</xmax>
			<ymax>176</ymax>
		</bndbox>
	</object>
</annotation>