<?xml version="1.0" ?><annotation verified="no">
	<folder>VOC2007</folder>
	<filename>33.jpg</filename>
	
	<source>
		<database>Unknown</database>
	</source>
	<size>
		<width>385</width>
		<height>516</height>
		<depth>3</depth>
	</size>
	<segmented>0</segmented>
	<object>
		<name>sergio valente</name>
		<pose>Unspecified</pose>
		<truncated>0</truncated>
		<difficult>0</difficult>
		<bndbox>
			<xmin>54</xmin>
			<ymin>214</ymin>
			<xmax>341</xmax>
			<ymax>269</ymax>
		</bndbox>
	</object>
	<object>
		<name>sergio valente</name>
		<pose>Unspecified</pose>
		<truncated>0</truncated>
		<difficult>0</difficult>
		<bndbox>
			<xmin>131</xmin>
			<ymin>202</ymin>
			<xmax>230</xmax>
			<ymax>254</ymax>
		</bndbox>
	</object>
</annotation>