<annotation verified="no">
	<folder>Gulf Oil</folder>
	<filename>34.jpg</filename>
	<source>
		<database>Unknown</database>
	</source>
	<size>
		<width>493</width>
		<height>387</height>
		<depth>3</depth>
	</size>
	<segmented>0</segmented>
	<object>
		<name>Gulf Oil</name>
		<pose>Unspecified</pose>
		<truncated>0</truncated>
		<difficult>0</difficult>
		<bndbox>
			<xmin>17</xmin>
			<ymin>29</ymin>
			<xmax>474</xmax>
			<ymax>363</ymax>
		</bndbox>
	</object>
</annotation>
