<annotation verified="no">
	<folder>Eden Cheese</folder>
	<filename>40.jpg</filename>
	<source>
		<database>Unknown</database>
	</source>
	<size>
		<width>485</width>
		<height>383</height>
		<depth>3</depth>
	</size>
	<segmented>0</segmented>
	<object>
		<name>Eden Cheese</name>
		<pose>Unspecified</pose>
		<truncated>0</truncated>
		<difficult>0</difficult>
		<bndbox>
			<xmin>73</xmin>
			<ymin>206</ymin>
			<xmax>175</xmax>
			<ymax>275</ymax>
		</bndbox>
	</object>
	<object>
		<name>Eden Cheese</name>
		<pose>Unspecified</pose>
		<truncated>0</truncated>
		<difficult>0</difficult>
		<bndbox>
			<xmin>58</xmin>
			<ymin>296</ymin>
			<xmax>147</xmax>
			<ymax>366</ymax>
		</bndbox>
	</object>
</annotation>
