<?xml version="1.0" ?><annotation verified="no">
	<folder>bahama breeze</folder>
	<filename>45.jpg</filename>
	<source>
		<database>Unknown</database>
	</source>
	<size>
		<width>506</width>
		<height>360</height>
		<depth>3</depth>
	</size>
	<segmented>0</segmented>
	<object>
		<name>bahama breeze</name>
		<pose>Unspecified</pose>
		<truncated>0</truncated>
		<difficult>0</difficult>
		<bndbox>
			<xmin>22</xmin>
			<ymin>12</ymin>
			<xmax>432</xmax>
			<ymax>208</ymax>
		</bndbox>
	</object>
</annotation>