<annotation verified="no">
	<folder>Colnago</folder>
	<filename>15.jpg</filename>
	<source>
		<database>Unknown</database>
	</source>
	<size>
		<width>487</width>
		<height>363</height>
		<depth>3</depth>
	</size>
	<segmented>0</segmented>
	<object>
		<name>Colnago</name>
		<pose>Unspecified</pose>
		<truncated>0</truncated>
		<difficult>0</difficult>
		<bndbox>
			<xmin>48</xmin>
			<ymin>53</ymin>
			<xmax>363</xmax>
			<ymax>130</ymax>
		</bndbox>
	</object>
	<object>
		<name>Colnago</name>
		<pose>Unspecified</pose>
		<truncated>0</truncated>
		<difficult>0</difficult>
		<bndbox>
			<xmin>205</xmin>
			<ymin>167</ymin>
			<xmax>470</xmax>
			<ymax>219</ymax>
		</bndbox>
	</object>
	<object>
		<name>Colnago</name>
		<pose>Unspecified</pose>
		<truncated>0</truncated>
		<difficult>0</difficult>
		<bndbox>
			<xmin>206</xmin>
			<ymin>219</ymin>
			<xmax>464</xmax>
			<ymax>268</ymax>
		</bndbox>
	</object>
</annotation>
