<?xml version="1.0" ?><annotation verified="no">
	<folder>VOC2007</folder>
	<filename>1.jpg</filename>
	
	<source>
		<database>Unknown</database>
	</source>
	<size>
		<width>495</width>
		<height>378</height>
		<depth>3</depth>
	</size>
	<segmented>0</segmented>
	<object>
		<name>BaDuYoua</name>
		<pose>Unspecified</pose>
		<truncated>0</truncated>
		<difficult>0</difficult>
		<bndbox>
			<xmin>210</xmin>
			<ymin>133</ymin>
			<xmax>394</xmax>
			<ymax>235</ymax>
		</bndbox>
	</object>
	<object>
		<name>BaDuYoua</name>
		<pose>Unspecified</pose>
		<truncated>0</truncated>
		<difficult>0</difficult>
		<bndbox>
			<xmin>92</xmin>
			<ymin>121</ymin>
			<xmax>202</xmax>
			<ymax>235</ymax>
		</bndbox>
	</object>
</annotation>