<?xml version="1.0" ?><annotation>
	<folder>macro</folder>
	<filename>130.jpg</filename>
	<source>
		<database>Unknown</database>
	</source>
	<size>
		<width>523</width>
		<height>369</height>
		<depth>3</depth>
	</size>
	<segmented>0</segmented>
	<object>
		<name>macro</name>
		<pose>Unspecified</pose>
		<truncated>0</truncated>
		<difficult>0</difficult>
		<bndbox>
			<xmin>8</xmin>
			<ymin>10</ymin>
			<xmax>65</xmax>
			<ymax>52</ymax>
		</bndbox>
	</object>
</annotation>