<?xml version="1.0" ?><annotation verified="no">
	<folder>corzo</folder>
	<filename>16.jpg</filename>
	<source>
		<database>Unknown</database>
	</source>
	<size>
		<width>507</width>
		<height>369</height>
		<depth>1</depth>
	</size>
	<segmented>0</segmented>
	<object>
		<name>corzo</name>
		<pose>Unspecified</pose>
		<truncated>0</truncated>
		<difficult>0</difficult>
		<bndbox>
			<xmin>7</xmin>
			<ymin>155</ymin>
			<xmax>157</xmax>
			<ymax>221</ymax>
		</bndbox>
	</object>
</annotation>