<annotation verified="no">
	<folder>Marie Callender's</folder>
	<filename>16.jpg</filename>
	<source>
		<database>Unknown</database>
	</source>
	<size>
		<width>395</width>
		<height>504</height>
		<depth>3</depth>
	</size>
	<segmented>0</segmented>
	<object>
		<name>Marie Callender's</name>
		<pose>Unspecified</pose>
		<truncated>0</truncated>
		<difficult>0</difficult>
		<bndbox>
			<xmin>36</xmin>
			<ymin>313</ymin>
			<xmax>121</xmax>
			<ymax>357</ymax>
		</bndbox>
	</object>
	<object>
		<name>Marie Callender's</name>
		<pose>Unspecified</pose>
		<truncated>0</truncated>
		<difficult>0</difficult>
		<bndbox>
			<xmin>63</xmin>
			<ymin>238</ymin>
			<xmax>166</xmax>
			<ymax>289</ymax>
		</bndbox>
	</object>
</annotation>
