<?xml version="1.0" ?><annotation verified="no">
	<folder>lincoln logs</folder>
	<filename>55.jpg</filename>
	<source>
		<database>Unknown</database>
	</source>
	<size>
		<width>377</width>
		<height>513</height>
		<depth>3</depth>
	</size>
	<segmented>0</segmented>
	<object>
		<name>lincoln logs</name>
		<pose>Unspecified</pose>
		<truncated>0</truncated>
		<difficult>0</difficult>
		<bndbox>
			<xmin>100</xmin>
			<ymin>150</ymin>
			<xmax>327</xmax>
			<ymax>211</ymax>
		</bndbox>
	</object>
</annotation>