<?xml version="1.0" ?><annotation verified="no">
	<folder>VOC2007</folder>
	<filename>20.jpg</filename>
	
	<source>
		<database>Unknown</database>
	</source>
	<size>
		<width>505</width>
		<height>395</height>
		<depth>3</depth>
	</size>
	<segmented>0</segmented>
	<object>
		<name>Billy Jealousy</name>
		<pose>Unspecified</pose>
		<truncated>0</truncated>
		<difficult>0</difficult>
		<bndbox>
			<xmin>69</xmin>
			<ymin>6</ymin>
			<xmax>154</xmax>
			<ymax>159</ymax>
		</bndbox>
	</object>
	<object>
		<name>Billy Jealousy</name>
		<pose>Unspecified</pose>
		<truncated>0</truncated>
		<difficult>0</difficult>
		<bndbox>
			<xmin>170</xmin>
			<ymin>74</ymin>
			<xmax>379</xmax>
			<ymax>115</ymax>
		</bndbox>
	</object>
	<object>
		<name>Billy Jealousy</name>
		<pose>Unspecified</pose>
		<truncated>0</truncated>
		<difficult>0</difficult>
		<bndbox>
			<xmin>263</xmin>
			<ymin>187</ymin>
			<xmax>281</xmax>
			<ymax>218</ymax>
		</bndbox>
	</object>
	<object>
		<name>Billy Jealousy</name>
		<pose>Unspecified</pose>
		<truncated>0</truncated>
		<difficult>0</difficult>
		<bndbox>
			<xmin>321</xmin>
			<ymin>198</ymin>
			<xmax>339</xmax>
			<ymax>229</ymax>
		</bndbox>
	</object>
	<object>
		<name>Billy Jealousy</name>
		<pose>Unspecified</pose>
		<truncated>0</truncated>
		<difficult>0</difficult>
		<bndbox>
			<xmin>377</xmin>
			<ymin>202</ymin>
			<xmax>392</xmax>
			<ymax>229</ymax>
		</bndbox>
	</object>
	<object>
		<name>Billy Jealousy</name>
		<pose>Unspecified</pose>
		<truncated>0</truncated>
		<difficult>0</difficult>
		<bndbox>
			<xmin>423</xmin>
			<ymin>207</ymin>
			<xmax>439</xmax>
			<ymax>233</ymax>
		</bndbox>
	</object>
	<object>
		<name>Billy Jealousy</name>
		<pose>Unspecified</pose>
		<truncated>0</truncated>
		<difficult>0</difficult>
		<bndbox>
			<xmin>457</xmin>
			<ymin>235</ymin>
			<xmax>468</xmax>
			<ymax>255</ymax>
		</bndbox>
	</object>
</annotation>