<?xml version="1.0" ?><annotation verified="yes">
	<folder>VOC2007</folder>
	<filename>55.jpg</filename>
	
	<source>
		<database>Unknown</database>
	</source>
	<size>
		<width>375</width>
		<height>483</height>
		<depth>3</depth>
	</size>
	<segmented>0</segmented>
	<object>
		<name>pritt stick</name>
		<pose>Unspecified</pose>
		<truncated>0</truncated>
		<difficult>0</difficult>
		<bndbox>
			<xmin>153</xmin>
			<ymin>149</ymin>
			<xmax>223</xmax>
			<ymax>209</ymax>
		</bndbox>
	</object>
	<object>
		<name>pritt stick</name>
		<pose>Unspecified</pose>
		<truncated>0</truncated>
		<difficult>0</difficult>
		<bndbox>
			<xmin>273</xmin>
			<ymin>181</ymin>
			<xmax>327</xmax>
			<ymax>223</ymax>
		</bndbox>
	</object>
	<object>
		<name>pritt stick</name>
		<pose>Unspecified</pose>
		<truncated>0</truncated>
		<difficult>0</difficult>
		<bndbox>
			<xmin>47</xmin>
			<ymin>222</ymin>
			<xmax>95</xmax>
			<ymax>251</ymax>
		</bndbox>
	</object>
</annotation>