<?xml version="1.0" ?><annotation verified="yes">
	<folder>VOC2007</folder>
	<filename>21.jpg</filename>
	
	<source>
		<database>Unknown</database>
	</source>
	<size>
		<width>518</width>
		<height>388</height>
		<depth>1</depth>
	</size>
	<segmented>0</segmented>
	<object>
		<name>Alfani</name>
		<pose>Unspecified</pose>
		<truncated>1</truncated>
		<difficult>0</difficult>
		<bndbox>
			<xmin>3</xmin>
			<ymin>68</ymin>
			<xmax>508</xmax>
			<ymax>269</ymax>
		</bndbox>
	</object>
</annotation>