<?xml version="1.0" ?><annotation verified="yes">
	<folder>VOC2007</folder>
	<filename>97.jpg</filename>
	
	<source>
		<database>Unknown</database>
	</source>
	<size>
		<width>518</width>
		<height>394</height>
		<depth>3</depth>
	</size>
	<segmented>0</segmented>
	<object>
		<name>Aveeno</name>
		<pose>Unspecified</pose>
		<truncated>0</truncated>
		<difficult>0</difficult>
		<bndbox>
			<xmin>96</xmin>
			<ymin>166</ymin>
			<xmax>181</xmax>
			<ymax>246</ymax>
		</bndbox>
	</object>
</annotation>