<?xml version="1.0" ?><annotation verified="yes">
	<folder>VOC2007</folder>
	<filename>133.jpg</filename>
	
	<source>
		<database>Unknown</database>
	</source>
	<size>
		<width>500</width>
		<height>399</height>
		<depth>3</depth>
	</size>
	<segmented>0</segmented>
	<object>
		<name>seventh generation</name>
		<pose>Unspecified</pose>
		<truncated>0</truncated>
		<difficult>0</difficult>
		<bndbox>
			<xmin>130</xmin>
			<ymin>226</ymin>
			<xmax>357</xmax>
			<ymax>356</ymax>
		</bndbox>
	</object>
</annotation>