<?xml version="1.0" ?><annotation>
	<folder>VOC2007</folder>
	<filename>87.jpg</filename>
	
	<source>
		<database>Unknown</database>
	</source>
	<size>
		<width>524</width>
		<height>383</height>
		<depth>3</depth>
	</size>
	<segmented>0</segmented>
	<object>
		<name>vegas robaina</name>
		<pose>Unspecified</pose>
		<truncated>0</truncated>
		<difficult>0</difficult>
		<bndbox>
			<xmin>98</xmin>
			<ymin>130</ymin>
			<xmax>191</xmax>
			<ymax>210</ymax>
		</bndbox>
	</object>
	<object>
		<name>vegas robaina</name>
		<pose>Unspecified</pose>
		<truncated>0</truncated>
		<difficult>0</difficult>
		<bndbox>
			<xmin>281</xmin>
			<ymin>135</ymin>
			<xmax>358</xmax>
			<ymax>225</ymax>
		</bndbox>
	</object>
	<object>
		<name>vegas robaina</name>
		<pose>Unspecified</pose>
		<truncated>0</truncated>
		<difficult>0</difficult>
		<bndbox>
			<xmin>373</xmin>
			<ymin>219</ymin>
			<xmax>458</xmax>
			<ymax>279</ymax>
		</bndbox>
	</object>
</annotation>