<annotation verified="yes">
	<folder>IQinVision</folder>
	<filename>44.jpg</filename>
	<source>
		<database>Unknown</database>
	</source>
	<size>
		<width>378</width>
		<height>481</height>
		<depth>3</depth>
	</size>
	<segmented>0</segmented>
	<object>
		<name>IQinVision</name>
		<pose>Unspecified</pose>
		<truncated>1</truncated>
		<difficult>0</difficult>
		<bndbox>
			<xmin>34</xmin>
			<ymin>1</ymin>
			<xmax>173</xmax>
			<ymax>56</ymax>
		</bndbox>
	</object>
</annotation>
