<?xml version="1.0" ?><annotation verified="no">
	<folder>VOC2007</folder>
	<filename>11.jpg</filename>
	
	<source>
		<database>Unknown</database>
	</source>
	<size>
		<width>516</width>
		<height>382</height>
		<depth>3</depth>
	</size>
	<segmented>0</segmented>
	<object>
		<name>Chipsmore</name>
		<pose>Unspecified</pose>
		<truncated>0</truncated>
		<difficult>0</difficult>
		<bndbox>
			<xmin>262</xmin>
			<ymin>92</ymin>
			<xmax>389</xmax>
			<ymax>188</ymax>
		</bndbox>
	</object>
	<object>
		<name>Chipsmore</name>
		<pose>Unspecified</pose>
		<truncated>0</truncated>
		<difficult>0</difficult>
		<bndbox>
			<xmin>37</xmin>
			<ymin>72</ymin>
			<xmax>111</xmax>
			<ymax>136</ymax>
		</bndbox>
	</object>
	<object>
		<name>Chipsmore</name>
		<pose>Unspecified</pose>
		<truncated>0</truncated>
		<difficult>0</difficult>
		<bndbox>
			<xmin>155</xmin>
			<ymin>295</ymin>
			<xmax>212</xmax>
			<ymax>344</ymax>
		</bndbox>
	</object>
</annotation>